tiny_orm.py
tiny_orm-0.0.1.dist-info/METADATA
tiny_orm-0.0.1.dist-info/WHEEL
tiny_orm-0.0.1.dist-info/top_level.txt
tiny_orm-0.0.1.dist-info/RECORD
