Metadata-Version: 2.1
Name: tiny-orm
Version: 0.0.1
Summary: A tiny ORM for SQLite
Home-page: https://github.com/xzmeng/tiny-orm
Author: Meng Xiangzhuo
License: MIT License
Platform: UNKNOWN
Classifier: Development Status :: 4 - Beta
Classifier: License :: OSI Approved :: MIT License
Classifier: Natural Language :: English
Classifier: Operating System :: OS Independent
Classifier: Programming Language :: Python :: 2
Classifier: Programming Language :: Python :: 3
Requires-Python: >=3.6
